CHANGES.rst
MANIFEST.in
README.rst
setup.py
docs/LICENSE.GPL
docs/LICENSE.txt
src/EXTERNALS.txt
src/Products/__init__.py
src/Products.MeetingIDEA.egg-info/PKG-INFO
src/Products.MeetingIDEA.egg-info/SOURCES.txt
src/Products.MeetingIDEA.egg-info/dependency_links.txt
src/Products.MeetingIDEA.egg-info/namespace_packages.txt
src/Products.MeetingIDEA.egg-info/not-zip-safe
src/Products.MeetingIDEA.egg-info/requires.txt
src/Products.MeetingIDEA.egg-info/top_level.txt
src/Products/MeetingIDEA/README.txt
src/Products/MeetingIDEA/__init__.py
src/Products/MeetingIDEA/adapters.py
src/Products/MeetingIDEA/config.py
src/Products/MeetingIDEA/configure.zcml
src/Products/MeetingIDEA/interfaces.py
src/Products/MeetingIDEA/overrides.zcml
src/Products/MeetingIDEA/profiles.zcml
src/Products/MeetingIDEA/refresh.txt
src/Products/MeetingIDEA/setuphandlers.py
src/Products/MeetingIDEA/testing.py
src/Products/MeetingIDEA/testing.zcml
src/Products/MeetingIDEA/version.txt
src/Products/MeetingIDEA/Extensions/__init__.py
src/Products/MeetingIDEA/browser/__init__.py
src/Products/MeetingIDEA/browser/configure.zcml
src/Products/MeetingIDEA/browser/overrides.py
src/Products/MeetingIDEA/locales/PloneMeeting.pot
src/Products/MeetingIDEA/locales/imio.actionspanel.pot
src/Products/MeetingIDEA/locales/imio.history.pot
src/Products/MeetingIDEA/locales/plone.pot
src/Products/MeetingIDEA/locales/sync_pos.sh
src/Products/MeetingIDEA/locales/fr/LC_MESSAGES/PloneMeeting.po
src/Products/MeetingIDEA/locales/fr/LC_MESSAGES/imio.actionspanel.po
src/Products/MeetingIDEA/locales/fr/LC_MESSAGES/imio.history.po
src/Products/MeetingIDEA/locales/fr/LC_MESSAGES/plone.po
src/Products/MeetingIDEA/migrations/__init__.py
src/Products/MeetingIDEA/migrations/migrate_strategic_axis.py
src/Products/MeetingIDEA/migrations/migrate_to_4_1.py
src/Products/MeetingIDEA/model/MeetingIDEA.zargo
src/Products/MeetingIDEA/model/__init__.py
src/Products/MeetingIDEA/model/generate.conf
src/Products/MeetingIDEA/model/generate.sh
src/Products/MeetingIDEA/model/pm_updates.py
src/Products/MeetingIDEA/profiles/__init__.py
src/Products/MeetingIDEA/profiles/default/MeetingIDEA_marker.txt
src/Products/MeetingIDEA/profiles/default/__init__.py
src/Products/MeetingIDEA/profiles/default/cssregistry.xml
src/Products/MeetingIDEA/profiles/default/import_steps.xml
