Metadata-Version: 2.1
Name: Products.MeetingIDEA
Version: 4.1.9
Summary: Official meetings management for college and council of belgiancommunes (PloneMeeting extension profile)
Home-page: https://www.imio.be/nos-applications/ia-delib
Author: Gauthier Bastien
Author-email: gauthier@imio.be
License: GPL
Platform: UNKNOWN
Classifier: Environment :: Web Environment
Classifier: Framework :: Plone
Classifier: Framework :: Plone :: 4.3
Classifier: License :: OSI Approved :: GNU General Public License (GPL)
Classifier: Programming Language :: Python
Classifier: Programming Language :: Python :: 2.7
Provides-Extra: templates
Provides-Extra: test
